<markers><marker loc="North America" label="North America" lat="14.62" lng="-90.5353">    <infowindow><![CDATA[                            <li class="gm-half float-left">                    <a class="is-current" href="#region-north-america" data-reveal="region-north-america" data-reveal-group="tabbed-widget">North America</a>                </li><font color="black"><a href="#">Guatemala</a><br><a href="#">Haiti</a><br><a href="#">Honduras</a><br><a href="#">Mexico</a><br><a href="#">Nicaragua</a><br><a href="#">USA</a><br>         ]]></infowindow>   </marker><marker loc="South America" label="South America" lat="-16.290154" lng="-63.58865300000002">    <infowindow><![CDATA[                            <li class="gm-half float-left">                    <a class="is-current" href="#region-south-america" data-reveal="region-south-america" data-reveal-group="tabbed-widget">South America</a>                </li><font color="black"><a href="#">Bolivia</a><br><a href="#">Ecuador</a><br><a href="#">Peru</a><br>         ]]></infowindow>   </marker><marker loc="Europe" label="Europe" lat="40.069099" lng="45.03818899999999">    <infowindow><![CDATA[                            <li class="gm-half float-left">                    <a class="is-current" href="#region-europe" data-reveal="region-europe" data-reveal-group="tabbed-widget">Europe</a>                </li><font color="black"><a href="#">Armenia</a><br><a href="#">Romania</a><br><a href="#">Georgia</a><br><a href="#">Ukraine</a><br>         ]]></infowindow>   </marker><marker loc="Africa" label="Africa" lat="6" lng="12">    <infowindow><![CDATA[                            <li class="gm-half float-left">                    <a class="is-current" href="#region-africa" data-reveal="region-africa" data-reveal-group="tabbed-widget">Africa</a>                </li><font color="black"><a href="#">Cameroon</a><br><a href="#">Ghana</a><br><a href="#">Kenya</a><br><a href="#">Malawi</a><br><a href="#">Rwanda</a><br><a href="#">Senegal</a><br><a href="#">South Africa</a><br><a href="#">Tanzania</a><br><a href="#">Uganda</a><br><a href="#">Zambia</a><br><a href="#">Zimbabwe</a><br>------------------<br>         ]]></infowindow></marker><marker loc="Asia" label="Asia" lat="23.684994" lng="90.35633099999995">    <infowindow><![CDATA[                            <li class="gm-half float-left">                    <a class="is-current" href="#region-asia" data-reveal="region-asia" data-reveal-group="tabbed-widget">Asia</a>                </li><font color="black"><a href="#">Bangladesh</a><br><a href="#">Cambodia</a><br><a href="#">China</a><br><a href="#">India</a><br><a href="#">Nepal</a><br><a href="#">Philippines</a><br><a href="#">Vietnam</a><br>         ]]></infowindow>   </marker>    </markers>